supersight
