Metadata-Version: 1.0
Name: supersight
Version: 0.2.5
Summary: A static website generator for MatplotLib plots
Home-page: https://github.com/CamilleMo/SuperSight
Author: Camille Moatti
Author-email: camille.moatti@gmail.com
License: Copyright (c) 2017, Camille Moatti
